main.py
apricity/objects/Bases/RouteBase.py
apricity/objects/Bases/SusurrusBase.py
apricity/objects/Bases/__init__.py
apricity/objects/Log/Log.py
apricity/objects/Log/__init__.py
apricity/services/TestRoute.py
apricity/services/Router/Router.py
apricity/services/Router/__init__.py
apricity/settings/__init__.py
apricity/settings/auth.py
apricity/settings/master_control.py
apricity/settings/routing.py
apricity/settings/types.py
colemen_equari_flow_tests-0.0.1.dist-info/METADATA
colemen_equari_flow_tests-0.0.1.dist-info/WHEEL
colemen_equari_flow_tests-0.0.1.dist-info/top_level.txt
colemen_equari_flow_tests-0.0.1.dist-info/RECORD
